xadmin/__init__.py
xadmin/adminx.py
xadmin/apps.py
xadmin/filters.py
xadmin/forms.py
xadmin/layout.py
xadmin/models.py
xadmin/sites.py
xadmin/util.py
xadmin/vendors.py
xadmin/widgets.py
xadmin/locale/de_DE/LC_MESSAGES/django.mo
xadmin/locale/de_DE/LC_MESSAGES/django.po
xadmin/locale/de_DE/LC_MESSAGES/djangojs.mo
xadmin/locale/de_DE/LC_MESSAGES/djangojs.po
xadmin/locale/en/LC_MESSAGES/django.mo
xadmin/locale/en/LC_MESSAGES/django.po
xadmin/locale/en/LC_MESSAGES/djangojs.mo
xadmin/locale/en/LC_MESSAGES/djangojs.po
xadmin/locale/es_MX/LC_MESSAGES/django.mo
xadmin/locale/es_MX/LC_MESSAGES/django.po
xadmin/locale/es_MX/LC_MESSAGES/djangojs.mo
xadmin/locale/es_MX/LC_MESSAGES/djangojs.po
xadmin/locale/eu/LC_MESSAGES/django.mo
xadmin/locale/eu/LC_MESSAGES/django.po
xadmin/locale/eu/LC_MESSAGES/djangojs.mo
xadmin/locale/eu/LC_MESSAGES/djangojs.po
xadmin/locale/id_ID/LC_MESSAGES/django.mo
xadmin/locale/id_ID/LC_MESSAGES/django.po
xadmin/locale/id_ID/LC_MESSAGES/djangojs.mo
xadmin/locale/id_ID/LC_MESSAGES/djangojs.po
xadmin/locale/ja/LC_MESSAGES/django.mo
xadmin/locale/ja/LC_MESSAGES/django.po
xadmin/locale/ja/LC_MESSAGES/djangojs.mo
xadmin/locale/ja/LC_MESSAGES/djangojs.po
xadmin/locale/lt/LC_MESSAGES/django.mo
xadmin/locale/lt/LC_MESSAGES/django.po
xadmin/locale/lt/LC_MESSAGES/djangojs.mo
xadmin/locale/lt/LC_MESSAGES/djangojs.po
xadmin/locale/nl_NL/LC_MESSAGES/django.mo
xadmin/locale/nl_NL/LC_MESSAGES/django.po
xadmin/locale/nl_NL/LC_MESSAGES/djangojs.mo
xadmin/locale/nl_NL/LC_MESSAGES/djangojs.po
xadmin/locale/pl/LC_MESSAGES/django.mo
xadmin/locale/pl/LC_MESSAGES/django.po
xadmin/locale/pl/LC_MESSAGES/djangojs.mo
xadmin/locale/pl/LC_MESSAGES/djangojs.po
xadmin/locale/pt_BR/LC_MESSAGES/django.mo
xadmin/locale/pt_BR/LC_MESSAGES/django.po
xadmin/locale/pt_BR/LC_MESSAGES/djangojs.mo
xadmin/locale/pt_BR/LC_MESSAGES/djangojs.po
xadmin/locale/ru_RU/LC_MESSAGES/django.mo
xadmin/locale/ru_RU/LC_MESSAGES/django.po
xadmin/locale/ru_RU/LC_MESSAGES/djangojs.mo
vxadmin-2.0.1.dist-info/LICENSE
vxadmin-2.0.1.dist-info/METADATA
vxadmin-2.0.1.dist-info/WHEEL
vxadmin-2.0.1.dist-info/top_level.txt
vxadmin-2.0.1.dist-info/RECORD
