Metadata-Version: 2.1
Name: vxadmin
Version: 2.0.1
Summary: A feature-rich django management system based on xadmin.
Home-page: http://www.xadmin.io
Author: sshwsfc
Author-email: sshwsfc@gmail.com
License: Copyright (c) Django Xadmin and individual contributors.
Requires-Dist: django (>=2)
Requires-Dist: django-crispy-forms (>=1.6.0)
Requires-Dist: django-import-export (>=0.5.1)
Requires-Dist: django-reversion (>=2.0.0)
Requires-Dist: django-formtools (==2.1)
Requires-Dist: future (==0.15.2)
Requires-Dist: httplib2 (==0.9.2)
Requires-Dist: six (==1.10.0)
Provides-Extra: excel
Requires-Dist: xlwt ; extra == 'excel'
Requires-Dist: xlsxwriter ; extra == 'excel'
Provides-Extra: reversion
Requires-Dist: django-reversion (>=2.0.0) ; extra == 'reversion'
